my_pkg/__init__.py
my_pkg/_version.py
my_pkg/cli.py
my_pkg/my_pkg.py
my_pkg_478-0.0.17.dist-info/METADATA
my_pkg_478-0.0.17.dist-info/WHEEL
my_pkg_478-0.0.17.dist-info/entry_points.txt
my_pkg_478-0.0.17.dist-info/top_level.txt
my_pkg_478-0.0.17.dist-info/RECORD
