Metadata-Version: 2.1
Name: my-pkg-478
Version: 0.0.17
Summary: My package
Home-page: https://github.com/CurtLH/my_pkg
Author: Curtis Hampton
Author-email: CurtLHampton@gmail.com
License: UNKNOWN
Keywords: my_pkg
Platform: UNKNOWN
Classifier: Programming Language :: Python :: 3.6
Classifier: Programming Language :: Python :: 3.7
Provides-Extra: dev
Requires-Dist: pytest ; extra == 'dev'
Requires-Dist: sphinx ; extra == 'dev'
